{
  "lastUpdated": "2026-07-14T12:01:08.134Z",
  "market": {
    "vnIndex": null,
    "hnxIndex": null,
    "usdVnd": {
      "value": 26450,
      "source": "Vietcombank"
    },
    "goldVnd": null,
    "goldUsd": {
      "value": 4035,
      "unit": "USD/oz",
      "source": "Yahoo Finance"
    },
    "marketOpen": false,
    "note": "Thị trường đóng cửa — hiển thị giá đóng cửa gần nhất"
  },
  "globalIndices": [
    {
      "symbol": "^GSPC",
      "name": "S&P 500",
      "region": "US",
      "value": 7515.34,
      "change": -22.090000000000146,
      "changePercent": -0.2930707150845865
    },
    {
      "symbol": "^IXIC",
      "name": "Nasdaq",
      "region": "US",
      "value": 25873.176,
      "change": -247.98400000000038,
      "changePercent": -0.9493605950118617
    },
    {
      "symbol": "^N225",
      "name": "Nikkei",
      "region": "Asia",
      "value": 67743.5,
      "change": 924.4499999999971,
      "changePercent": 1.3835126359922763
    },
    {
      "symbol": "^HSI",
      "name": "Hang Seng",
      "region": "Asia",
      "value": 24340.73,
      "change": 843.8400000000001,
      "changePercent": 3.5912837826623023
    },
    {
      "symbol": "^GDAXI",
      "name": "DAX",
      "region": "Europe",
      "value": 24911.25,
      "change": -554,
      "changePercent": -2.1755136902249146
    }
  ],
  "themes": [
    {
      "key": "stocks",
      "displayName": "Chứng khoán",
      "articles": [
        {
          "title": "Tại sao chiết khấu b&aacute;n lẻ xăng dầu giảm mạnh?",
          "link": "https://thanhnien.vn/tai-sao-chiet-khau-ban-le-xang-dau-giam-manh-185260714150506924.htm",
          "pubDate": "2026-07-14T12:00:00.000Z",
          "excerpt": "Khi gi&aacute; dầu thế giới biến động tăng mạnh, chiết khấu b&aacute;n lẻ xăng dầu trong nước lại lao dốc, nhiều nơi chỉ 5 - 20 đồng/l&iacute;t, thậm…",
          "sourceId": "thanhnien",
          "sourceName": "Thanh Niên",
          "sourceUrl": "https://thanhnien.vn",
          "attribution": "Thanh Niên"
        },
        {
          "title": "Cục Thuế lưu &yacute; điểm mới về khai thuế bổ sung, ho&agrave;n thuế tự động",
          "link": "https://thanhnien.vn/cuc-thue-luu-y-diem-moi-ve-khai-thue-bo-sung-hoan-thue-tu-dong-185260713102248125.htm",
          "pubDate": "2026-07-14T11:20:00.000Z",
          "excerpt": "Từ 1.7, người nộp thuế ph&aacute;t hiện hồ sơ khai thuế đ&atilde; nộp c&oacute; sai s&oacute;t được khai bổ sung trong 5 năm (trước đ&acirc;y l&agrave; 10…",
          "sourceId": "thanhnien",
          "sourceName": "Thanh Niên",
          "sourceUrl": "https://thanhnien.vn",
          "attribution": "Thanh Niên"
        },
        {
          "title": "Phát ngôn của chủ tiệm vàng Kim Lý trước khi bị khởi tố gây chú ý: \"Mình làm đúng thì không có gì phải sợ\"",
          "link": "https://cafef.vn/phat-ngon-cua-chu-tiem-vang-kim-ly-truoc-khi-bi-khoi-to-gay-chu-y-minh-lam-dung-thi-khong-co-gi-phai-so-188260714164455948.chn",
          "pubDate": "2026-07-14T11:18:00.000Z",
          "excerpt": "Ngày 14/7, Cơ quan công an đã khởi tố bà Lê Thị Ngọc Mỹ (chủ tiệm vàng Kim Lý) cùng 2 chủ tiệm vàng và 1 nhân viên kiểm định thuộc Công ty TNHH một thành viên…",
          "sourceId": "cafef",
          "sourceName": "CafeF",
          "sourceUrl": "https://cafef.vn",
          "attribution": "CafeF"
        },
        {
          "title": "The Global City khuấy động m&ugrave;a h&egrave; với h&agrave;ng loạt trải nghiệm lần đầu c&oacute; tại TP.HCM",
          "link": "https://thanhnien.vn/the-global-city-khuay-dong-mua-he-voi-hang-loat-trai-nghiem-lan-dau-co-tai-tphcm-185260714174603804.htm",
          "pubDate": "2026-07-14T10:38:00.000Z",
          "excerpt": "Kh&ocirc;ng cần đi xa khỏi TP.HCM, giới trẻ v&agrave; c&aacute;c gia đ&igrave;nh vẫn c&oacute; thể tận hưởng loạt hoạt động giải tr&iacute; mang tinh thần quốc…",
          "sourceId": "thanhnien",
          "sourceName": "Thanh Niên",
          "sourceUrl": "https://thanhnien.vn",
          "attribution": "Thanh Niên"
        },
        {
          "title": "Sau thời gian tăng n&oacute;ng, gi&aacute; căn hộ tr&ecirc;n thị trường sơ cấp đ&atilde; giảm",
          "link": "https://thanhnien.vn/sau-thoi-gian-tang-nong-gia-can-ho-tren-thi-truong-so-cap-da-giam-185260714164237138.htm",
          "pubDate": "2026-07-14T10:35:00.000Z",
          "excerpt": "C&aacute;c c&ocirc;ng ty nghi&ecirc;n cứu thị trường trong b&aacute;o c&aacute;o qu&yacute; 2/2026 đều nhận định, gi&aacute; b&aacute;n căn hộ tr&ecirc;n thị…",
          "sourceId": "thanhnien",
          "sourceName": "Thanh Niên",
          "sourceUrl": "https://thanhnien.vn",
          "attribution": "Thanh Niên"
        },
        {
          "title": "Thủ đoạn lừa đảo hàng trăm tỷ đồng của cựu CEO Công ty cổ phần tư vấn đầu tư Sao Vàng",
          "link": "https://cafef.vn/thu-doan-lua-dao-hang-tram-ty-dong-cua-cuu-ceo-cong-ty-co-phan-tu-van-dau-tu-sao-vang-188260714164126033.chn",
          "pubDate": "2026-07-14T10:32:00.000Z",
          "excerpt": "Huỳnh Thị Ngân Trang, cựu Tổng giám đốc Công ty cổ phần tư vấn đầu tư Sao Vàng đưa ra các chương trình hợp tác đầu tư với cam kết lợi nhuận từ 22-30%/năm, cam…",
          "sourceId": "cafef",
          "sourceName": "CafeF",
          "sourceUrl": "https://cafef.vn",
          "attribution": "CafeF"
        },
        {
          "title": "Một cổ phiếu lớn bị tự doanh CTCK \"xả\" 150 tỷ đồng phiên 14/7",
          "link": "https://cafef.vn/mot-co-phieu-lon-bi-tu-doanh-ctck-xa-150-ty-dong-phien-14-7-188260714165417125.chn",
          "pubDate": "2026-07-14T09:54:00.000Z",
          "excerpt": "Tự doanh CTCK bán ròng 100 tỷ đồng trên HOSE.",
          "sourceId": "cafef",
          "sourceName": "CafeF",
          "sourceUrl": "https://cafef.vn",
          "attribution": "CafeF"
        },
        {
          "title": "V&igrave; sao si&ecirc;u s&acirc;n bay Long Th&agrave;nh muốn vừa khai th&aacute;c vừa khắc phục lỗi ph&aacute;t sinh?",
          "link": "https://thanhnien.vn/vi-sao-sieu-san-bay-long-thanh-muon-vua-khai-thac-vua-khac-phuc-loi-phat-sinh-185260714163825465.htm",
          "pubDate": "2026-07-14T09:47:00.000Z",
          "excerpt": "Trong b&aacute;o c&aacute;o vừa gửi Cục H&agrave;ng kh&ocirc;ng, Tổng c&ocirc;ng ty Cảng h&agrave;ng kh&ocirc;ng Việt Nam (ACV) dự kiến si&ecirc;u cảng Long…",
          "sourceId": "thanhnien",
          "sourceName": "Thanh Niên",
          "sourceUrl": "https://thanhnien.vn",
          "attribution": "Thanh Niên"
        }
      ],
      "aiSummary": null
    },
    {
      "key": "realestate",
      "displayName": "Bất động sản",
      "articles": [
        {
          "title": "Tại sao chiết khấu b&aacute;n lẻ xăng dầu giảm mạnh?",
          "link": "https://thanhnien.vn/tai-sao-chiet-khau-ban-le-xang-dau-giam-manh-185260714150506924.htm",
          "pubDate": "2026-07-14T12:00:00.000Z",
          "excerpt": "Khi gi&aacute; dầu thế giới biến động tăng mạnh, chiết khấu b&aacute;n lẻ xăng dầu trong nước lại lao dốc, nhiều nơi chỉ 5 - 20 đồng/l&iacute;t, thậm…",
          "sourceId": "thanhnien",
          "sourceName": "Thanh Niên",
          "sourceUrl": "https://thanhnien.vn",
          "attribution": "Thanh Niên"
        },
        {
          "title": "Ba tác động định hình lại thị trường bất động sản",
          "link": "https://cafef.vn/ba-tac-dong-dinh-hinh-lai-thi-truong-bat-dong-san-18826071416482815.chn",
          "pubDate": "2026-07-14T11:47:00.000Z",
          "excerpt": "Thị trường bất động sản Việt Nam đang định hình một chu kỳ phát triển mới, dẫn dắt bởi quy hoạch, hạ tầng, minh bạch thông tin và nhu cầu thực.",
          "sourceId": "cafef",
          "sourceName": "CafeF",
          "sourceUrl": "https://cafef.vn",
          "attribution": "CafeF"
        },
        {
          "title": "Cục Thuế lưu &yacute; điểm mới về khai thuế bổ sung, ho&agrave;n thuế tự động",
          "link": "https://thanhnien.vn/cuc-thue-luu-y-diem-moi-ve-khai-thue-bo-sung-hoan-thue-tu-dong-185260713102248125.htm",
          "pubDate": "2026-07-14T11:20:00.000Z",
          "excerpt": "Từ 1.7, người nộp thuế ph&aacute;t hiện hồ sơ khai thuế đ&atilde; nộp c&oacute; sai s&oacute;t được khai bổ sung trong 5 năm (trước đ&acirc;y l&agrave; 10…",
          "sourceId": "thanhnien",
          "sourceName": "Thanh Niên",
          "sourceUrl": "https://thanhnien.vn",
          "attribution": "Thanh Niên"
        },
        {
          "title": "The Global City khuấy động m&ugrave;a h&egrave; với h&agrave;ng loạt trải nghiệm lần đầu c&oacute; tại TP.HCM",
          "link": "https://thanhnien.vn/the-global-city-khuay-dong-mua-he-voi-hang-loat-trai-nghiem-lan-dau-co-tai-tphcm-185260714174603804.htm",
          "pubDate": "2026-07-14T10:38:00.000Z",
          "excerpt": "Kh&ocirc;ng cần đi xa khỏi TP.HCM, giới trẻ v&agrave; c&aacute;c gia đ&igrave;nh vẫn c&oacute; thể tận hưởng loạt hoạt động giải tr&iacute; mang tinh thần quốc…",
          "sourceId": "thanhnien",
          "sourceName": "Thanh Niên",
          "sourceUrl": "https://thanhnien.vn",
          "attribution": "Thanh Niên"
        },
        {
          "title": "Sau thời gian tăng n&oacute;ng, gi&aacute; căn hộ tr&ecirc;n thị trường sơ cấp đ&atilde; giảm",
          "link": "https://thanhnien.vn/sau-thoi-gian-tang-nong-gia-can-ho-tren-thi-truong-so-cap-da-giam-185260714164237138.htm",
          "pubDate": "2026-07-14T10:35:00.000Z",
          "excerpt": "C&aacute;c c&ocirc;ng ty nghi&ecirc;n cứu thị trường trong b&aacute;o c&aacute;o qu&yacute; 2/2026 đều nhận định, gi&aacute; b&aacute;n căn hộ tr&ecirc;n thị…",
          "sourceId": "thanhnien",
          "sourceName": "Thanh Niên",
          "sourceUrl": "https://thanhnien.vn",
          "attribution": "Thanh Niên"
        },
        {
          "title": "Khám phá hành trình nâng tầm phong cách sống tại Vlasta Premier - Phú Thuận",
          "link": "https://cafef.vn/kham-pha-hanh-trinh-nang-tam-phong-cach-song-tai-vlasta-premier-phu-thuan-188260714173917597.chn",
          "pubDate": "2026-07-14T10:30:00.000Z",
          "excerpt": "Giữa nhịp phát triển sôi động của Nam TP. Hồ Chí Minh Vlasta Premier - Phú Thuận dẫn dắt chủ nhân trải nghiệm một chuẩn mực sống cao cấp định hình chân dung…",
          "sourceId": "cafef",
          "sourceName": "CafeF",
          "sourceUrl": "https://cafef.vn",
          "attribution": "CafeF"
        },
        {
          "title": "Sonadezi Long Bình trả cổ tức năm 2025 bằng tiền tỷ lệ 45%",
          "link": "https://cafef.vn/sonadezi-long-binh-tra-co-tuc-nam-2025-bang-tien-ty-le-45-188260714170519623.chn",
          "pubDate": "2026-07-14T10:17:00.000Z",
          "excerpt": "Ngày 28/7/2026 tới, Sonadezi Long Bình sẽ chốt danh sách cổ đông để thực hiện chi trả cổ tức năm 2025 bằng tiền mặt với tỷ lệ 45%.",
          "sourceId": "cafef",
          "sourceName": "CafeF",
          "sourceUrl": "https://cafef.vn",
          "attribution": "CafeF"
        },
        {
          "title": "Dự án cải tạo hạ lưu sông Kim Ngưu gần 700 tỷ đồng giờ ra sao?",
          "link": "https://cafef.vn/du-an-cai-tao-ha-luu-song-kim-nguu-gan-700-ty-dong-gio-ra-sao-188260714165121962.chn",
          "pubDate": "2026-07-14T10:08:00.000Z",
          "excerpt": "Khởi công từ cuối năm 2025, dự án cải tạo tuyến hạ lưu sông Kim Ngưu dài gần 5,8 km hiện đã hoàn thành phần lớn hạng mục chính. Trên công trường, các đơn vị…",
          "sourceId": "cafef",
          "sourceName": "CafeF",
          "sourceUrl": "https://cafef.vn",
          "attribution": "CafeF"
        }
      ],
      "aiSummary": null
    },
    {
      "key": "macro",
      "displayName": "Vĩ mô / Đầu tư",
      "articles": [
        {
          "title": "Tại sao chiết khấu b&aacute;n lẻ xăng dầu giảm mạnh?",
          "link": "https://thanhnien.vn/tai-sao-chiet-khau-ban-le-xang-dau-giam-manh-185260714150506924.htm",
          "pubDate": "2026-07-14T12:00:00.000Z",
          "excerpt": "Khi gi&aacute; dầu thế giới biến động tăng mạnh, chiết khấu b&aacute;n lẻ xăng dầu trong nước lại lao dốc, nhiều nơi chỉ 5 - 20 đồng/l&iacute;t, thậm…",
          "sourceId": "thanhnien",
          "sourceName": "Thanh Niên",
          "sourceUrl": "https://thanhnien.vn",
          "attribution": "Thanh Niên"
        },
        {
          "title": "Cục Thuế lưu &yacute; điểm mới về khai thuế bổ sung, ho&agrave;n thuế tự động",
          "link": "https://thanhnien.vn/cuc-thue-luu-y-diem-moi-ve-khai-thue-bo-sung-hoan-thue-tu-dong-185260713102248125.htm",
          "pubDate": "2026-07-14T11:20:00.000Z",
          "excerpt": "Từ 1.7, người nộp thuế ph&aacute;t hiện hồ sơ khai thuế đ&atilde; nộp c&oacute; sai s&oacute;t được khai bổ sung trong 5 năm (trước đ&acirc;y l&agrave; 10…",
          "sourceId": "thanhnien",
          "sourceName": "Thanh Niên",
          "sourceUrl": "https://thanhnien.vn",
          "attribution": "Thanh Niên"
        },
        {
          "title": "Từ giữa tháng 6, toàn bộ người dân Việt Nam được miễn phí 1 dịch vụ",
          "link": "https://cafef.vn/tu-giua-thang-6-toan-bo-nguoi-dan-viet-nam-duoc-mien-phi-1-dich-vu-188260714152026703.chn",
          "pubDate": "2026-07-14T10:53:00.000Z",
          "excerpt": "Đã được miễn phí từ giữa tháng 6 song nhiều người vẫn chưa biết đây là dịch vụ gì.",
          "sourceId": "cafef",
          "sourceName": "CafeF",
          "sourceUrl": "https://cafef.vn",
          "attribution": "CafeF"
        },
        {
          "title": "The Global City khuấy động m&ugrave;a h&egrave; với h&agrave;ng loạt trải nghiệm lần đầu c&oacute; tại TP.HCM",
          "link": "https://thanhnien.vn/the-global-city-khuay-dong-mua-he-voi-hang-loat-trai-nghiem-lan-dau-co-tai-tphcm-185260714174603804.htm",
          "pubDate": "2026-07-14T10:38:00.000Z",
          "excerpt": "Kh&ocirc;ng cần đi xa khỏi TP.HCM, giới trẻ v&agrave; c&aacute;c gia đ&igrave;nh vẫn c&oacute; thể tận hưởng loạt hoạt động giải tr&iacute; mang tinh thần quốc…",
          "sourceId": "thanhnien",
          "sourceName": "Thanh Niên",
          "sourceUrl": "https://thanhnien.vn",
          "attribution": "Thanh Niên"
        },
        {
          "title": "Sau thời gian tăng n&oacute;ng, gi&aacute; căn hộ tr&ecirc;n thị trường sơ cấp đ&atilde; giảm",
          "link": "https://thanhnien.vn/sau-thoi-gian-tang-nong-gia-can-ho-tren-thi-truong-so-cap-da-giam-185260714164237138.htm",
          "pubDate": "2026-07-14T10:35:00.000Z",
          "excerpt": "C&aacute;c c&ocirc;ng ty nghi&ecirc;n cứu thị trường trong b&aacute;o c&aacute;o qu&yacute; 2/2026 đều nhận định, gi&aacute; b&aacute;n căn hộ tr&ecirc;n thị…",
          "sourceId": "thanhnien",
          "sourceName": "Thanh Niên",
          "sourceUrl": "https://thanhnien.vn",
          "attribution": "Thanh Niên"
        },
        {
          "title": "Cận cảnh cao tốc TP.HCM - Mộc Bài đồng loạt triển khai nhiều mũi thi công",
          "link": "https://cafef.vn/can-canh-cao-toc-tphcm-moc-bai-dong-loat-trien-khai-nhieu-mui-thi-cong-188260714154534501.chn",
          "pubDate": "2026-07-14T10:00:00.000Z",
          "excerpt": "Cao tốc TP.HCM - Mộc Bài dài 51 km đang đồng loạt triển khai nhiều mũi thi công, từ phát quang mặt bằng, làm đường gom dân sinh đến xây dựng cầu vượt ngang.",
          "sourceId": "cafef",
          "sourceName": "CafeF",
          "sourceUrl": "https://cafef.vn",
          "attribution": "CafeF"
        },
        {
          "title": "V&igrave; sao si&ecirc;u s&acirc;n bay Long Th&agrave;nh muốn vừa khai th&aacute;c vừa khắc phục lỗi ph&aacute;t sinh?",
          "link": "https://thanhnien.vn/vi-sao-sieu-san-bay-long-thanh-muon-vua-khai-thac-vua-khac-phuc-loi-phat-sinh-185260714163825465.htm",
          "pubDate": "2026-07-14T09:47:00.000Z",
          "excerpt": "Trong b&aacute;o c&aacute;o vừa gửi Cục H&agrave;ng kh&ocirc;ng, Tổng c&ocirc;ng ty Cảng h&agrave;ng kh&ocirc;ng Việt Nam (ACV) dự kiến si&ecirc;u cảng Long…",
          "sourceId": "thanhnien",
          "sourceName": "Thanh Niên",
          "sourceUrl": "https://thanhnien.vn",
          "attribution": "Thanh Niên"
        },
        {
          "title": "Bộ Công an lý giải quy định người thân phải thông báo lưu trú khi ở qua đêm",
          "link": "https://cafef.vn/bo-cong-an-ly-giai-quy-dinh-nguoi-than-phai-thong-bao-luu-tru-khi-o-qua-dem-188260714155329939.chn",
          "pubDate": "2026-07-14T09:35:00.000Z",
          "excerpt": "Mục đích của quy định mới là bảo đảm thông tin nơi ở thực tế của công dân được cập nhật đầy đủ, chính xác, phục vụ quản lý cư trú, bảo đảm an ninh, trật tự,…",
          "sourceId": "cafef",
          "sourceName": "CafeF",
          "sourceUrl": "https://cafef.vn",
          "attribution": "CafeF"
        }
      ],
      "aiSummary": null
    },
    {
      "key": "international",
      "displayName": "International",
      "articles": [
        {
          "title": "EU demands ‘youth mode’ to protect children from addictive social media features",
          "link": "https://www.scmp.com/news/world/europe/article/3360546/eu-demands-youth-mode-protect-children-addictive-social-media-features?utm_source=rss_feed",
          "pubDate": "2026-07-14T11:14:32.000Z",
          "excerpt": "There should be a “youth mode” for children on social media platforms in which addictive features and targeted advertising are turned off, EU lawmakers…",
          "sourceId": "scmp",
          "sourceName": "SCMP",
          "sourceUrl": "https://www.scmp.com",
          "attribution": "SCMP"
        },
        {
          "title": "Democrats are not in great shape",
          "link": "https://www.ft.com/content/bd5f3950-3c80-41af-852e-fe736da603ac",
          "pubDate": "2026-07-14T10:55:23.000Z",
          "excerpt": "A fractious opposition is doing everything it can to spurn an open goal",
          "sourceId": "ft",
          "sourceName": "Financial Times",
          "sourceUrl": "https://www.ft.com",
          "attribution": "FT"
        },
        {
          "title": "UK borrowing costs hit highest level since May as oil surges",
          "link": "https://www.ft.com/content/107fc895-14db-4003-baa0-d81ed29c477f",
          "pubDate": "2026-07-14T10:48:56.000Z",
          "excerpt": "Ten-year yield back above 5% just days before Andy Burnham set to become prime minister",
          "sourceId": "ft",
          "sourceName": "Financial Times",
          "sourceUrl": "https://www.ft.com",
          "attribution": "FT"
        },
        {
          "title": "Spain bull run injuries hit 57 after chaotic final day in Pamplona",
          "link": "https://www.scmp.com/news/world/europe/article/3360542/spain-bull-run-injuries-hit-57-after-chaotic-final-day-pamplona?utm_source=rss_feed",
          "pubDate": "2026-07-14T10:32:45.000Z",
          "excerpt": "Ten men suffered injuries on Tuesday during the eighth and final bull run of Spain’s famed San Fermin festival, bringing to 57 the total number of daredevils…",
          "sourceId": "scmp",
          "sourceName": "SCMP",
          "sourceUrl": "https://www.scmp.com",
          "attribution": "SCMP"
        },
        {
          "title": "JPMorgan and Goldman profits surge on blockbuster trading haul",
          "link": "https://www.ft.com/content/f4231724-bb67-4cfd-81e2-d20f4badb82e",
          "pubDate": "2026-07-14T09:29:58.000Z",
          "excerpt": "Wall Street banks seize on jolt of volatility in equities markets to post stronger than expected results",
          "sourceId": "ft",
          "sourceName": "Financial Times",
          "sourceUrl": "https://www.ft.com",
          "attribution": "FT"
        },
        {
          "title": "Watch: pomp and colour in Paris as France holds Bastille Day parade",
          "link": "https://www.scmp.com/news/world/europe/article/3360505/watch-pomp-and-colour-paris-france-holds-bastille-day-parade?utm_source=rss_feed",
          "pubDate": "2026-07-14T08:05:49.000Z",
          "excerpt": "Ukrainian fighter pilots and troops took pride of place in France’s national Bastille Day celebrations on Tuesday as a massive parade showcased support for…",
          "sourceId": "scmp",
          "sourceName": "SCMP",
          "sourceUrl": "https://www.scmp.com",
          "attribution": "SCMP"
        },
        {
          "title": "RIP the US state department",
          "link": "https://www.ft.com/content/ae268a4e-5134-4d34-ba5e-a908cc74c52d",
          "pubDate": "2026-07-14T04:00:08.000Z",
          "excerpt": "America’s diplomats used to have global sway. Now they are besieged by their own president",
          "sourceId": "ft",
          "sourceName": "Financial Times",
          "sourceUrl": "https://www.ft.com",
          "attribution": "FT"
        },
        {
          "title": "Why the world should copy Trump for once",
          "link": "https://www.ft.com/content/6ff504c6-1cee-4e37-a56d-6a06c3107819",
          "pubDate": "2026-07-14T04:00:08.000Z",
          "excerpt": "The US is offering $1,000 to fund investment accounts for children born during the president’s second term",
          "sourceId": "ft",
          "sourceName": "Financial Times",
          "sourceUrl": "https://www.ft.com",
          "attribution": "FT"
        }
      ],
      "aiSummary": null
    }
  ]
}